figures/__init__.py
figures/area_calculator.py
tests/__init__.py
tests/test.py
geomathlib-1.0.1.dist-info/METADATA
geomathlib-1.0.1.dist-info/WHEEL
geomathlib-1.0.1.dist-info/top_level.txt
geomathlib-1.0.1.dist-info/RECORD
