Metadata-Version: 2.1
Name: geomathlib
Version: 1.0.1
Summary: A library for geometric calculations
Author: Alexandr Medvedev
Author-email: alex.mmdvdvv@gmail.com
